MANIFEST.in
README.rst
setup.cfg
setup.py
fui/__init__.py
fui.fsbrowse.egg-info/PKG-INFO
fui.fsbrowse.egg-info/SOURCES.txt
fui.fsbrowse.egg-info/dependency_links.txt
fui.fsbrowse.egg-info/entry_points.txt
fui.fsbrowse.egg-info/namespace_packages.txt
fui.fsbrowse.egg-info/not-zip-safe
fui.fsbrowse.egg-info/paster_plugins.txt
fui.fsbrowse.egg-info/requires.txt
fui.fsbrowse.egg-info/top_level.txt
fui/fsbrowse/__init__.py
fui/fsbrowse/config.py
fui/fsbrowse/configure.zcml
fui/fsbrowse/interfaces.py
fui/fsbrowse/browser/__init__.py
fui/fsbrowse/browser/configure.zcml
fui/fsbrowse/browser/fsbrowse.pt
fui/fsbrowse/browser/fsbrowse.py
fui/fsbrowse/browser/fsfile_base.py
fui/fsbrowse/browser/raw.py
fui/fsbrowse/browser/style.css
fui/fsbrowse/content/__init__.py
fui/fsbrowse/content/configure.zcml
fui/fsbrowse/content/filesystemfolder.py
fui/fsbrowse/profiles/default/catalog.xml
fui/fsbrowse/profiles/default/cssregistry.xml
fui/fsbrowse/profiles/default/factorytool.xml
fui/fsbrowse/profiles/default/rolemap.xml
fui/fsbrowse/profiles/default/types.xml
fui/fsbrowse/profiles/default/types/FilesystemFolder.xml
fui/fsbrowse/tests/__init__.py
fui/fsbrowse/tests/base.py
fui/fsbrowse/tests/test_doctest.py