Metadata-Version: 1.0
Name: fui.fsbrowse
Version: 0.4
Summary: UNKNOWN
Home-page: http://github.com/espenak/fui.fsbrowse
Author: Espen A. Kristiansen
Author-email: post@espenak.net
License: GPL
Platform: UNKNOWN
Classifier: Framework :: Plone
Classifier: Programming Language :: Python
Classifier: Topic :: Software Development :: Libraries :: Python Modules
